{
  "timestamp": "2025-12-25T14:39:54.863Z",
  "batch": {
    "batch": 3,
    "count": 100
  },
  "deviations": [
    {
      "type": "distribution",
      "bucket": "elite_55+",
      "actual": "0.0%",
      "target": "10.0%",
      "deviation": "10.0%",
      "severity": "MEDIUM"
    },
    {
      "type": "distribution",
      "bucket": "strong_45-54",
      "actual": "7.0%",
      "target": "25.0%",
      "deviation": "18.0%",
      "severity": "HIGH"
    },
    {
      "type": "distribution",
      "bucket": "good_40-44",
      "actual": "78.0%",
      "target": "40.0%",
      "deviation": "38.0%",
      "severity": "HIGH"
    }
  ],
  "recommendations": [
    "Add more funded startups from TechCrunch/YC"
  ]
}